{
  "timestamp": "2026-04-04T19:01:35.488884",
  "total_segments": 4176,
  "accept_count": 3930,
  "pending_count": 159,
  "reject_count": 87,
  "composition_rate": 94.11,
  "calibration": {
    "tau_accept": 0.7677201625438445,
    "tau_accept_ci_95": [
      0.7568437526123128,
      0.7749286287195937
    ],
    "tau_reject": 0.65,
    "n_known_good": 3988,
    "n_known_bad": 4,
    "n_bootstrap": 1000,
    "timestamp": "2026-04-04T19:01:35.429369"
  },
  "dimension_statistics": {
    "S_unprompted": {
      "mean": 0.9938,
      "std": 0.0278,
      "p5": 0.9564,
      "p95": 1.0,
      "min": 0.5,
      "max": 1.0
    },
    "S_gap": {
      "mean": 1.0,
      "std": 0.0,
      "p5": 1.0,
      "p95": 1.0,
      "min": 1.0,
      "max": 1.0
    },
    "S_snr": {
      "mean": 1.0,
      "std": 0.0,
      "p5": 1.0,
      "p95": 1.0,
      "min": 1.0,
      "max": 1.0
    },
    "S_duration": {
      "mean": 0.7759,
      "std": 0.196,
      "p5": 0.3844,
      "p95": 0.9825,
      "min": 0.0,
      "max": 0.9999
    },
    "S_confidence": {
      "mean": 0.5,
      "std": 0.0,
      "p5": 0.5,
      "p95": 0.5,
      "min": 0.5,
      "max": 0.5
    },
    "S_boundary": {
      "mean": 1.0,
      "std": 0.0,
      "p5": 1.0,
      "p95": 1.0,
      "min": 0.9984,
      "max": 1.0
    }
  },
  "per_script_breakdown": {
    "1": {
      "accept": 283,
      "pending": 10,
      "reject": 5,
      "total": 298
    },
    "2": {
      "accept": 1171,
      "pending": 38,
      "reject": 25,
      "total": 1234
    },
    "3": {
      "accept": 800,
      "pending": 40,
      "reject": 25,
      "total": 865
    },
    "4": {
      "accept": 923,
      "pending": 50,
      "reject": 17,
      "total": 990
    },
    "5": {
      "accept": 753,
      "pending": 21,
      "reject": 15,
      "total": 789
    }
  },
  "human_review_count": 183
}